desispec/__init__.py
desispec/_version.py
desispec/averagefluxcalibration.py
desispec/badcolumn.py
desispec/bootcalib.py
desispec/calibfinder.py
desispec/ccdcalib.py
desispec/coaddition.py
desispec/correct_cte.py
desispec/cosmics.py
desispec/darktrail.py
desispec/desi_bias_dark_1d_model.py
desispec/desi_create_bias_dark.py
desispec/desi_dashboard.py
desispec/desi_proc_time_distribution.py
desispec/efftime.py
desispec/emlinefit.py
desispec/exposure_qa.py
desispec/fiberbitmasking.py
desispec/fibercrosstalk.py
desispec/fiberflat.py
desispec/fiberflat_vs_humidity.py
desispec/fiberfluxcorr.py
desispec/fluxcalibration.py
desispec/focus.py
desispec/frame.py
desispec/gpu.py
desispec/heliocentric.py
desispec/image.py
desispec/image_model.py
desispec/interpolation.py
desispec/joincosmics.py
desispec/large_trace_shifts.py
desispec/linalg.py
desispec/log.py
desispec/magnitude.py
desispec/maskbits.py
desispec/maskedmedian.py
desispec/mgii_afterburner.py
desispec/night_qa.py
desispec/parallel.py
desispec/pixflat.py
desispec/pixgroup.py
desispec/preproc.py
desispec/resolution.py
desispec/scatteredlight.py
desispec/sky.py
desispec/skycorr.py
desispec/skygradpca.py
desispec/skymag.py
desispec/specscore.py
desispec/specstatus.py
desispec/spectra.py
desispec/tile_qa.py
desispec/tile_qa_plot.py
desispec/tilecompleteness.py
desispec/tpcorrparam.py
desispec/trace_shifts.py
desispec/tsnr.py
desispec/util.py
desispec/validredshifts.py
desispec/xytraceset.py
desispec/zcatalog.py
desispec/zmtl.py
desispec/data/batch_config.yaml
desispec/data/fiber-crosstalk.yaml
desispec/data/spec-arc-lamps.dat
desispec/data/spec-sky.dat
desispec/data/arc_lines/ArI_air.ascii
desispec/data/arc_lines/ArI_vacuum.ascii
desispec/data/arc_lines/CdI_air.ascii
desispec/data/arc_lines/CdI_vacuum.ascii
desispec/data/arc_lines/HeI_vacuum.ascii
desispec/data/arc_lines/HgI_air.ascii
desispec/data/arc_lines/HgI_vacuum.ascii
desispec/data/arc_lines/KrI_air.ascii
desispec/data/arc_lines/KrI_vacuum.ascii
desispec-0.70.0.dist-info/licenses/LICENSE.rst
desispec-0.70.0.dist-info/METADATA
desispec-0.70.0.dist-info/WHEEL
desispec-0.70.0.dist-info/top_level.txt
desispec-0.70.0.dist-info/zip-safe
desispec-0.70.0.dist-info/RECORD
