Metadata-Version: 2.4
Name: desispec
Version: 0.70.0
Summary: DESI Spectroscopic Tools
Home-page: https://github.com/desihub/desispec
Author: DESI Collaboration
Author-email: desi-data@desi.lbl.gov
License: BSD-3-Clause
Requires-Python: >=3.10
License-File: LICENSE.rst
Requires-Dist: pytz
Requires-Dist: requests
Requires-Dist: astropy
Requires-Dist: scipy
Requires-Dist: fitsio
Requires-Dist: numba
Requires-Dist: healpy
Requires-Dist: speclite
Requires-Dist: sqlalchemy
Requires-Dist: desiutil
Requires-Dist: desitarget
Requires-Dist: desimodel
Provides-Extra: all
Provides-Extra: test
Requires-Dist: pytest; extra == "test"
Provides-Extra: coverage
Requires-Dist: pytest-cov; extra == "coverage"
Requires-Dist: coveralls; extra == "coverage"
Provides-Extra: doc
Requires-Dist: Sphinx; extra == "doc"
Requires-Dist: sphinx-rtd-theme; extra == "doc"
Dynamic: license-file
